{ "results": [

    {
        "iPad_Id": 1,
        "iPadSerialNumber": "miC1swkZhq7OvbZJ"
    },

    {
        "iPad_Id": 2,
        "iPadSerialNumber": "lo4cWpEOhzbGEZj2"
    },

    {
        "iPad_Id": 3,
        "iPadSerialNumber": "FXoRIsHIu8qv911S"
    },

    {
        "iPad_Id": 4,
        "iPadSerialNumber": "IzArOMhwALYjxGpz"
    },

    {
        "iPad_Id": 5,
        "iPadSerialNumber": "1AmmS6O3saDNREtv"
    },

    {
        "iPad_Id": 6,
        "iPadSerialNumber": "V9HLmGjEHFu9Ka31"
    },

    {
        "iPad_Id": 7,
        "iPadSerialNumber": "piZ2egrZ66ncEEGn"
    },

    {
        "iPad_Id": 8,
        "iPadSerialNumber": "BrasV9S6oTF5JbWm"
    },

    {
        "iPad_Id": 9,
        "iPadSerialNumber": "HUEowznvmBZT11Ed"
    },

    {
        "iPad_Id": 10,
        "iPadSerialNumber": "ce83Fkaxy08u61GO"
    },

    {
        "iPad_Id": 11,
        "iPadSerialNumber": "Hjnd9NqQw1ZE1Q45"
    },

    {
        "iPad_Id": 12,
        "iPadSerialNumber": "l892lbPjg9hjm4dA"
    },

    {
        "iPad_Id": 13,
        "iPadSerialNumber": "YwztD66NM23MgYPJ"
    },

    {
        "iPad_Id": 14,
        "iPadSerialNumber": "Q4Nd6Yaxd4GiMD3N"
    },

    {
        "iPad_Id": 15,
        "iPadSerialNumber": "IkyNhuh6zsrayeNH"
    },

    {
        "iPad_Id": 16,
        "iPadSerialNumber": "rWpTkM2JeFDi0IK8"
    },

    {
        "iPad_Id": 17,
        "iPadSerialNumber": "AfIKw15rPBnINEXj"
    },

    {
        "iPad_Id": 18,
        "iPadSerialNumber": "E1GaWX3tqTXMH9gX"
    },

    {
        "iPad_Id": 19,
        "iPadSerialNumber": "6Oqg9FWE4iuJmuaW"
    },

    {
        "iPad_Id": 20,
        "iPadSerialNumber": "8TAu672Oebrw4zEC"
    },

    {
        "iPad_Id": 21,
        "iPadSerialNumber": "l8fnpYtnz4JySsqC"
    },

    {
        "iPad_Id": 22,
        "iPadSerialNumber": "jBZmL7raspgUkros"
    },

    {
        "iPad_Id": 23,
        "iPadSerialNumber": "uOSMfiq7au4DdIJG"
    },

    {
        "iPad_Id": 24,
        "iPadSerialNumber": "8grHBy4gfJZH7XRs"
    },

    {
        "iPad_Id": 25,
        "iPadSerialNumber": "gGSDW1bafVJE5dvs"
    },

    {
        "iPad_Id": 26,
        "iPadSerialNumber": "JFt08pmdJ6CUYWR3"
    },

    {
        "iPad_Id": 27,
        "iPadSerialNumber": "LFTBCtnnJud3umna"
    },

    {
        "iPad_Id": 28,
        "iPadSerialNumber": "guEDaHl3ebruyYS8"
    },

    {
        "iPad_Id": 29,
        "iPadSerialNumber": "8wG1XZ8wJfr8MhF4"
    },

    {
        "iPad_Id": 30,
        "iPadSerialNumber": "CcwyqfWYWAYWQi77"
    },

    {
        "iPad_Id": 31,
        "iPadSerialNumber": "4cDdp4lnk98eSxc5"
    },

    {
        "iPad_Id": 32,
        "iPadSerialNumber": "foF6NlvzTKXILezS"
    },

    {
        "iPad_Id": 33,
        "iPadSerialNumber": "weeDpuix3i5tan1q"
    },

    {
        "iPad_Id": 34,
        "iPadSerialNumber": "3sQWepXBbXDd041c"
    },

    {
        "iPad_Id": 35,
        "iPadSerialNumber": "9jxhKyjBqZs7C4YP"
    },

    {
        "iPad_Id": 36,
        "iPadSerialNumber": "xYSgGDoljb1lHau6"
    },

    {
        "iPad_Id": 37,
        "iPadSerialNumber": "eIFHMi3cAVdY6aNb"
    },

    {
        "iPad_Id": 38,
        "iPadSerialNumber": "r7JlA5RKYJapESiN"
    },

    {
        "iPad_Id": 39,
        "iPadSerialNumber": "xbA1pqc71bktm4fp"
    },

    {
        "iPad_Id": 40,
        "iPadSerialNumber": "kS8Tczm1ujg2Aini"
    },

    {
        "iPad_Id": 41,
        "iPadSerialNumber": "QmRqJz9ZcIMRh13L"
    },

    {
        "iPad_Id": 42,
        "iPadSerialNumber": "RVGayiLEK8RQU234"
    },

    {
        "iPad_Id": 43,
        "iPadSerialNumber": "hQhPJTlxFFxCoAyW"
    },

    {
        "iPad_Id": 44,
        "iPadSerialNumber": "LGK1SXTPVQBO9Xi0"
    },

    {
        "iPad_Id": 45,
        "iPadSerialNumber": "Opo3njWOLVnTcQWA"
    },

    {
        "iPad_Id": 46,
        "iPadSerialNumber": "3qChnouLXg1tVGVS"
    },

    {
        "iPad_Id": 47,
        "iPadSerialNumber": "uAjxkAFitWCOXsua"
    },

    {
        "iPad_Id": 48,
        "iPadSerialNumber": "WTZNg9pboZKtOx1N"
    },

    {
        "iPad_Id": 49,
        "iPadSerialNumber": "9j5wI7ridCWoSxco"
    },

    {
        "iPad_Id": 50,
        "iPadSerialNumber": "qOuVdJZU1y8VCFpD"
    },

    {
        "iPad_Id": 51,
        "iPadSerialNumber": "IA4M2DZacErK95pz"
    },

    {
        "iPad_Id": 52,
        "iPadSerialNumber": "53SokH1ae3KPgKOC"
    },

    {
        "iPad_Id": 53,
        "iPadSerialNumber": "wNIDVrWV6mRkRGWT"
    },

    {
        "iPad_Id": 54,
        "iPadSerialNumber": "sXXuSMJ5cpgjZrba"
    },

    {
        "iPad_Id": 55,
        "iPadSerialNumber": "wnJnZJWiXnRVyPZV"
    },

    {
        "iPad_Id": 56,
        "iPadSerialNumber": "Icfqf9JBY2VamVXn"
    },

    {
        "iPad_Id": 57,
        "iPadSerialNumber": "75h4DpX2sFRgW45z"
    },

    {
        "iPad_Id": 58,
        "iPadSerialNumber": "Sh8opOezgfx84jTy"
    },

    {
        "iPad_Id": 59,
        "iPadSerialNumber": "TxyyRQyGce618mtM"
    },

    {
        "iPad_Id": 60,
        "iPadSerialNumber": "CRGMMhXTiYHcdjBo"
    },

    {
        "iPad_Id": 61,
        "iPadSerialNumber": "vDKbwVyE5takLRfq"
    },

    {
        "iPad_Id": 62,
        "iPadSerialNumber": "Q7GobNPOXKj0Hy7A"
    },

    {
        "iPad_Id": 63,
        "iPadSerialNumber": "kFg7vjIVGpN1anJY"
    },

    {
        "iPad_Id": 64,
        "iPadSerialNumber": "nTFEMNGWp1t0Mbjw"
    },

    {
        "iPad_Id": 65,
        "iPadSerialNumber": "wj17Swy03WG3yxHw"
    },

    {
        "iPad_Id": 66,
        "iPadSerialNumber": "fJzRUSObkOzKSERe"
    },

    {
        "iPad_Id": 67,
        "iPadSerialNumber": "eBhtdlU78gFOOlps"
    },

    {
        "iPad_Id": 68,
        "iPadSerialNumber": "P9JADxyceqPDpBDn"
    },

    {
        "iPad_Id": 69,
        "iPadSerialNumber": "XC8FVHksgd0lhjkz"
    },

    {
        "iPad_Id": 70,
        "iPadSerialNumber": "gAEzkVCYKlKf5fDi"
    },

    {
        "iPad_Id": 71,
        "iPadSerialNumber": "r6ycRkjmG6fILuBi"
    },

    {
        "iPad_Id": 72,
        "iPadSerialNumber": "lP6vP3DTMXWbMAWA"
    },

    {
        "iPad_Id": 73,
        "iPadSerialNumber": "IMeBKANoXsXr6Rqh"
    },

    {
        "iPad_Id": 74,
        "iPadSerialNumber": "y5g6jxmojP3T26Nf"
    },

    {
        "iPad_Id": 75,
        "iPadSerialNumber": "gu8tiCeL8EhgZ78s"
    },

    {
        "iPad_Id": 76,
        "iPadSerialNumber": "fC4ZnAG9sQREf2Wu"
    },

    {
        "iPad_Id": 77,
        "iPadSerialNumber": "ao57Myjs4teGf5dx"
    },

    {
        "iPad_Id": 78,
        "iPadSerialNumber": "4UiMCsVW78AeYfIp"
    },

    {
        "iPad_Id": 79,
        "iPadSerialNumber": "0nM5lCTphUxRv7hm"
    },

    {
        "iPad_Id": 80,
        "iPadSerialNumber": "nK3w0uMS2bWt3D73"
    },

    {
        "iPad_Id": 81,
        "iPadSerialNumber": "vOZHkug5tp5edtCx"
    },

    {
        "iPad_Id": 82,
        "iPadSerialNumber": "Sqxbun9Kb3wL1dIr"
    },

    {
        "iPad_Id": 83,
        "iPadSerialNumber": "xRZyozq4V3lmjG3V"
    },

    {
        "iPad_Id": 84,
        "iPadSerialNumber": "ABjt9KLICzTnl9tT"
    },

    {
        "iPad_Id": 85,
        "iPadSerialNumber": "geYuG0p6gPi0hkgK"
    },

    {
        "iPad_Id": 86,
        "iPadSerialNumber": "QkyEDnvlvPo18JtJ"
    },

    {
        "iPad_Id": 87,
        "iPadSerialNumber": "0NcwixRjgpncylYP"
    },

    {
        "iPad_Id": 88,
        "iPadSerialNumber": "atPqDvRkLgqgmR1O"
    },

    {
        "iPad_Id": 89,
        "iPadSerialNumber": "vhPSFnM6mmHB1eAz"
    },

    {
        "iPad_Id": 90,
        "iPadSerialNumber": "ybaVNO2tdt6DnDuj"
    },

    {
        "iPad_Id": 91,
        "iPadSerialNumber": "opK8y4igSdso5sBU"
    },

    {
        "iPad_Id": 92,
        "iPadSerialNumber": "W3Q9VY3Ts5Lsg2QF"
    },

    {
        "iPad_Id": 93,
        "iPadSerialNumber": "586f3McsyKcx3MsU"
    },

    {
        "iPad_Id": 94,
        "iPadSerialNumber": "bpn0qalUK0xhATDi"
    },

    {
        "iPad_Id": 95,
        "iPadSerialNumber": "F7cOpm9ikpIn7HUx"
    },

    {
        "iPad_Id": 96,
        "iPadSerialNumber": "fyfHylqm8UAIr7p0"
    },

    {
        "iPad_Id": 97,
        "iPadSerialNumber": "ZJyvYLQQTxFrQNmx"
    },

    {
        "iPad_Id": 98,
        "iPadSerialNumber": "QRTccCF8ILAcvVOF"
    },

    {
        "iPad_Id": 99,
        "iPadSerialNumber": "B3mg6BgQKKAPXHlb"
    },

    {
        "iPad_Id": 100,
        "iPadSerialNumber": "Tk3RoZUL4BAecfhs"
    }

]}